flockcontext/__init__.py
flockcontext/flock.py
flockcontext/flock_open.py
flockcontext-0.4.0.dist-info/AUTHORS.rst
flockcontext-0.4.0.dist-info/LICENSE
flockcontext-0.4.0.dist-info/METADATA
flockcontext-0.4.0.dist-info/WHEEL
flockcontext-0.4.0.dist-info/top_level.txt
flockcontext-0.4.0.dist-info/RECORD
