Metadata-Version: 2.1
Name: flockcontext
Version: 0.4.0
Summary: Improves fcntl.flock usage
Home-page: https://github.com/AntoineCezar/flockcontext
Author: Antoine Cezar
Author-email: antoine@cezar.fr
License: BSD
Keywords: flock context
Platform: UNKNOWN
Classifier: Development Status :: 5 - Production/Stable
Classifier: Intended Audience :: Developers
Classifier: License :: OSI Approved :: BSD License
Classifier: Natural Language :: English
Classifier: Programming Language :: Python :: 2
Classifier: Programming Language :: Python :: 2.7
Classifier: Programming Language :: Python :: 3
Classifier: Programming Language :: Python :: 3.3
Classifier: Programming Language :: Python :: 3.4
Classifier: Programming Language :: Python :: 3.6
Classifier: Programming Language :: Python :: 3.7
Requires-Dist: timeoutcontext
